LICENSE
README.md
setup.py
pynhanes/__init__.py
pynhanes/activity.py
pynhanes/loader.py
pynhanes/scraper.py
pynhanes/userdata.py
pynhanes/utils.py
pynhanes/wgetxpt.py
pynhanes.egg-info/PKG-INFO
pynhanes.egg-info/SOURCES.txt
pynhanes.egg-info/dependency_links.txt
pynhanes.egg-info/entry_points.txt
pynhanes.egg-info/requires.txt
pynhanes.egg-info/top_level.txt