Metadata-Version: 2.1
Name: pynhanes
Version: 0.0.18
Summary: Python parser and scraper for NHANES accelerometry and questionnaire
Home-page: https://github.com/timpyrkov/pynhanes
Author: Tim Pyrkov
Author-email: tim.pyrkov@gmail.com
License: MIT License
Classifier: Programming Language :: Python :: 3
Classifier: License :: OSI Approved :: MIT License
Classifier: Topic :: Scientific/Engineering
Requires-Python: >=3.6
License-File: LICENSE
